{
    "first_para": "Alderman Maurice Devenney is a British politician from the Democratic Unionist Party representing Foyle in the Northern Ireland Assembly. He took office on the 20th October 2014 after succeeding retiring party member William Hay.", 
    "full": {
        "extract": "Alderman Maurice Devenney is a British politician from the Democratic Unionist Party representing Foyle in the Northern Ireland Assembly. He took office on the 20th October 2014 after succeeding retiring party member William Hay.\nSince 2005 he has been a member of Derry City Council and between 2011 and 2012 he served as Mayor of the city. \n^ [1]\n^ [2]\n^ [3]", 
        "ns": 0, 
        "pageid": 44174137, 
        "title": "Maurice Devenney"
    }
}