{
    "first_para": "Iain David Wright (born 9 May 1972) is a British Labour Party politician who has been the Member of Parliament (MP) for Hartlepool since 2004, and is currently the Shadow Minister for Industry. He was previously Parliamentary Under-Secretary of State with responsibility for apprenticeships and 14-19 reform in the Department for Children, Schools and Families until 11 May 2010.", 
    "full": {
        "extract": "Iain David Wright (born 9 May 1972) is a British Labour Party politician who has been the Member of Parliament (MP) for Hartlepool since 2004, and is currently the Shadow Minister for Industry. He was previously Parliamentary Under-Secretary of State with responsibility for apprenticeships and 14-19 reform in the Department for Children, Schools and Families until 11 May 2010.\n^ http://www.publications.parliament.uk/pa/cm/cmregmem/110124/part2.htm", 
        "ns": 0, 
        "pageid": 883609, 
        "title": "Iain Wright"
    }
}