{
    "first_para": "Dr Andrew William Murrison (born 24 April 1961, Colchester) is a doctor and Conservative Party politician in the United Kingdom. After serving as the Member of Parliament (MP) for Westbury from 2001 to 2010, at the 2010 general election he was elected for the new seat of South West Wiltshire, covering much of the same area, including the towns of Trowbridge, Warminster and Westbury.", 
    "full": {
        "extract": "Dr Andrew William Murrison (born 24 April 1961, Colchester) is a doctor and Conservative Party politician in the United Kingdom. After serving as the Member of Parliament (MP) for Westbury from 2001 to 2010, at the 2010 general election he was elected for the new seat of South West Wiltshire, covering much of the same area, including the towns of Trowbridge, Warminster and Westbury.", 
        "ns": 0, 
        "pageid": 435637, 
        "title": "Andrew Murrison"
    }
}